Workbook

Sheet Assumptions
A1: drivEV — Next 1,000 Cohort Model · Assumptions (illustrative)
A3: Parameter | B3: B2B Expand | C3: chargEV X-sell | D3: Salary Sacrifice | E3: Direct B2C
A4: Net unit target (info) | B4: 400 | C4: 150 | D4: 300 | E4: 150
A5: CAC (RM) | B5: 350 | C5: 600 | D5: 250 | E5: 1500
A6: Monthly churn % | B6: 0.005 | C6: 0.008 | D6: 0.01 | E6: 0.025
A7: Monthly revenue / unit (RM) | B7: 2600 | C7: 2600 | D7: 2400 | E7: 2900
A8: Contribution margin % | B8: 0.22 | C8: 0.22 | D8: 0.2 | E8: 0.18
A9: Avg asset value (RM) | B9: 170000 | C9: 170000 | D9: 150000 | E9: 200000
A10: 36-mo residual value (% of cost) | B10: 0.45 | C10: 0.45 | D10: 0.48 | E10: 0.42
A11: Avg tenor (months) | B11: 30 | C11: 30 | D11: 24 | E11: 18
A13: Capital structure (asset-light SPV)
A14: Senior sukuk — share / rate | B14: 0.7 | C14: 0.045
A15: Mezzanine — share / rate | B15: 0.2 | C15: 0.09
A16: Equity — share | B16: 0.1
A17: Residual value downside shock | B17: -0.15
A18: Opening book (existing units, B2B) | B18: 400

Sheet Model
A1: drivEV — 36-Month Cohort Model (editable; formulas reference Assumptions)
A2: Month | B2: Label | C2: Add B2B | D2: Add chgEV | E2: Add SalSac | F2: Add B2C | G2: Book B2B | H2: Book chgEV | I2: Book SalSac | J2: Book B2C | K2: Total Book | L2: Revenue | M2: Contribution | N2: CAC spend | O2: Net after CAC | P2: Asset base | Q2: Senior | R2: Mezz | S2: Equity | T2: Funding cost/mo
A3: 0 | B3: M0 (open) | C3: 0 | D3: 0 | E3: 0 | F3: 0 | G3: =Assumptions!$B$18 -> 400 | H3: 0 | I3: 0 | J3: 0 | K3: =SUM(G3:J3) -> 400 | L3: =G3*Assumptions!$B$7+H3*Assumptions!$C$7+I3*Assumptions!$D$7+J3*Assumptions!$E$7 -> 1040000 | M3: =G3*Assumptions!$B$7*Assumptions!$B$8+H3*Assumptions!$C$7*Assumptions!$C$8+I3*Assumptions!$D$7*Assumptions!$D$8+J3*Assumptions!$E$7*Assumptions!$E$8 -> 228800 | N3: =C3*Assumptions!$B$5+D3*Assumptions!$C$5+E3*Assumptions!$D$5+F3*Assumptions!$E$5 -> 0 | O3: =M3-N3 -> 228800 | P3: =G3*Assumptions!$B$9+H3*Assumptions!$C$9+I3*Assumptions!$D$9+J3*Assumptions!$E$9 -> 68000000 | Q3: =P3*Assumptions!$B$14 -> 47600000 | R3: =P3*Assumptions!$B$15 -> 13600000 | S3: =P3*Assumptions!$B$16 -> 6800000 | T3: =(Q3*Assumptions!$C$14+R3*Assumptions!$C$15)/12 -> 280500
A4: 1 | B4: M1 | C4: 54 | D4: 0 | E4: 0 | F4: 0 | G4: =G3+C4-ROUND(G3*Assumptions!$B$6,0) -> 452 | H4: =H3+D4-ROUND(H3*Assumptions!$C$6,0) -> 0 | I4: =I3+E4-ROUND(I3*Assumptions!$D$6,0) -> 0 | J4: =J3+F4-ROUND(J3*Assumptions!$E$6,0) -> 0 | K4: =SUM(G4:J4) -> 452 | L4: =G4*Assumptions!$B$7+H4*Assumptions!$C$7+I4*Assumptions!$D$7+J4*Assumptions!$E$7 -> 1175200 | M4: =G4*Assumptions!$B$7*Assumptions!$B$8+H4*Assumptions!$C$7*Assumptions!$C$8+I4*Assumptions!$D$7*Assumptions!$D$8+J4*Assumptions!$E$7*Assumptions!$E$8 -> 258544 | N4: =C4*Assumptions!$B$5+D4*Assumptions!$C$5+E4*Assumptions!$D$5+F4*Assumptions!$E$5 -> 18900 | O4: =M4-N4 -> 239644 | P4: =G4*Assumptions!$B$9+H4*Assumptions!$C$9+I4*Assumptions!$D$9+J4*Assumptions!$E$9 -> 76840000 | Q4: =P4*Assumptions!$B$14 -> 53788000 | R4: =P4*Assumptions!$B$15 -> 15368000 | S4: =P4*Assumptions!$B$16 -> 7684000 | T4: =(Q4*Assumptions!$C$14+R4*Assumptions!$C$15)/12 -> 316965
A5: 2 | B5: M2 | C5: 51 | D5: 0 | E5: 0 | F5: 0 | G5: =G4+C5-ROUND(G4*Assumptions!$B$6,0) -> 501 | H5: =H4+D5-ROUND(H4*Assumptions!$C$6,0) -> 0 | I5: =I4+E5-ROUND(I4*Assumptions!$D$6,0) -> 0 | J5: =J4+F5-ROUND(J4*Assumptions!$E$6,0) -> 0 | K5: =SUM(G5:J5) -> 501 | L5: =G5*Assumptions!$B$7+H5*Assumptions!$C$7+I5*Assumptions!$D$7+J5*Assumptions!$E$7 -> 1302600 | M5: =G5*Assumptions!$B$7*Assumptions!$B$8+H5*Assumptions!$C$7*Assumptions!$C$8+I5*Assumptions!$D$7*Assumptions!$D$8+J5*Assumptions!$E$7*Assumptions!$E$8 -> 286572 | N5: =C5*Assumptions!$B$5+D5*Assumptions!$C$5+E5*Assumptions!$D$5+F5*Assumptions!$E$5 -> 17850 | O5: =M5-N5 -> 268722 | P5: =G5*Assumptions!$B$9+H5*Assumptions!$C$9+I5*Assumptions!$D$9+J5*Assumptions!$E$9 -> 85170000 | Q5: =P5*Assumptions!$B$14 -> 59619000 | R5: =P5*Assumptions!$B$15 -> 17034000 | S5: =P5*Assumptions!$B$16 -> 8517000 | T5: =(Q5*Assumptions!$C$14+R5*Assumptions!$C$15)/12 -> 351326.25
A6: 3 | B6: M3 | C6: 48 | D6: 8 | E6: 0 | F6: 0 | G6: =G5+C6-ROUND(G5*Assumptions!$B$6,0) -> 546 | H6: =H5+D6-ROUND(H5*Assumptions!$C$6,0) -> 8 | I6: =I5+E6-ROUND(I5*Assumptions!$D$6,0) -> 0 | J6: =J5+F6-ROUND(J5*Assumptions!$E$6,0) -> 0 | K6: =SUM(G6:J6) -> 554 | L6: =G6*Assumptions!$B$7+H6*Assumptions!$C$7+I6*Assumptions!$D$7+J6*Assumptions!$E$7 -> 1440400 | M6: =G6*Assumptions!$B$7*Assumptions!$B$8+H6*Assumptions!$C$7*Assumptions!$C$8+I6*Assumptions!$D$7*Assumptions!$D$8+J6*Assumptions!$E$7*Assumptions!$E$8 -> 316888 | N6: =C6*Assumptions!$B$5+D6*Assumptions!$C$5+E6*Assumptions!$D$5+F6*Assumptions!$E$5 -> 21600 | O6: =M6-N6 -> 295288 | P6: =G6*Assumptions!$B$9+H6*Assumptions!$C$9+I6*Assumptions!$D$9+J6*Assumptions!$E$9 -> 94180000 | Q6: =P6*Assumptions!$B$14 -> 65926000 | R6: =P6*Assumptions!$B$15 -> 18836000 | S6: =P6*Assumptions!$B$16 -> 9418000 | T6: =(Q6*Assumptions!$C$14+R6*Assumptions!$C$15)/12 -> 388492.5
A7: 4 | B7: M4 | C7: 45 | D7: 8 | E7: 2 | F7: 0 | G7: =G6+C7-ROUND(G6*Assumptions!$B$6,0) -> 588 | H7: =H6+D7-ROUND(H6*Assumptions!$C$6,0) -> 16 | I7: =I6+E7-ROUND(I6*Assumptions!$D$6,0) -> 2 | J7: =J6+F7-ROUND(J6*Assumptions!$E$6,0) -> 0 | K7: =SUM(G7:J7) -> 606 | L7: =G7*Assumptions!$B$7+H7*Assumptions!$C$7+I7*Assumptions!$D$7+J7*Assumptions!$E$7 -> 1575200 | M7: =G7*Assumptions!$B$7*Assumptions!$B$8+H7*Assumptions!$C$7*Assumptions!$C$8+I7*Assumptions!$D$7*Assumptions!$D$8+J7*Assumptions!$E$7*Assumptions!$E$8 -> 346448 | N7: =C7*Assumptions!$B$5+D7*Assumptions!$C$5+E7*Assumptions!$D$5+F7*Assumptions!$E$5 -> 21050 | O7: =M7-N7 -> 325398 | P7: =G7*Assumptions!$B$9+H7*Assumptions!$C$9+I7*Assumptions!$D$9+J7*Assumptions!$E$9 -> 102980000 | Q7: =P7*Assumptions!$B$14 -> 72086000 | R7: =P7*Assumptions!$B$15 -> 20596000 | S7: =P7*Assumptions!$B$16 -> 10298000 | T7: =(Q7*Assumptions!$C$14+R7*Assumptions!$C$15)/12 -> 424792.5
A8: 5 | B8: M5 | C8: 43 | D8: 8 | E8: 3 | F8: 0 | G8: =G7+C8-ROUND(G7*Assumptions!$B$6,0) -> 628 | H8: =H7+D8-ROUND(H7*Assumptions!$C$6,0) -> 24 | I8: =I7+E8-ROUND(I7*Assumptions!$D$6,0) -> 5 | J8: =J7+F8-ROUND(J7*Assumptions!$E$6,0) -> 0 | K8: =SUM(G8:J8) -> 657 | L8: =G8*Assumptions!$B$7+H8*Assumptions!$C$7+I8*Assumptions!$D$7+J8*Assumptions!$E$7 -> 1707200 | M8: =G8*Assumptions!$B$7*Assumptions!$B$8+H8*Assumptions!$C$7*Assumptions!$C$8+I8*Assumptions!$D$7*Assumptions!$D$8+J8*Assumptions!$E$7*Assumptions!$E$8 -> 375344 | N8: =C8*Assumptions!$B$5+D8*Assumptions!$C$5+E8*Assumptions!$D$5+F8*Assumptions!$E$5 -> 20600 | O8: =M8-N8 -> 354744 | P8: =G8*Assumptions!$B$9+H8*Assumptions!$C$9+I8*Assumptions!$D$9+J8*Assumptions!$E$9 -> 111590000 | Q8: =P8*Assumptions!$B$14 -> 78113000 | R8: =P8*Assumptions!$B$15 -> 22318000 | S8: =P8*Assumptions!$B$16 -> 11159000 | T8: =(Q8*Assumptions!$C$14+R8*Assumptions!$C$15)/12 -> 460308.75
A9: 6 | B9: M6 | C9: 40 | D9: 8 | E9: 4 | F9: 0 | G9: =G8+C9-ROUND(G8*Assumptions!$B$6,0) -> 665 | H9: =H8+D9-ROUND(H8*Assumptions!$C$6,0) -> 32 | I9: =I8+E9-ROUND(I8*Assumptions!$D$6,0) -> 9 | J9: =J8+F9-ROUND(J8*Assumptions!$E$6,0) -> 0 | K9: =SUM(G9:J9) -> 706 | L9: =G9*Assumptions!$B$7+H9*Assumptions!$C$7+I9*Assumptions!$D$7+J9*Assumptions!$E$7 -> 1833800 | M9: =G9*Assumptions!$B$7*Assumptions!$B$8+H9*Assumptions!$C$7*Assumptions!$C$8+I9*Assumptions!$D$7*Assumptions!$D$8+J9*Assumptions!$E$7*Assumptions!$E$8 -> 403004 | N9: =C9*Assumptions!$B$5+D9*Assumptions!$C$5+E9*Assumptions!$D$5+F9*Assumptions!$E$5 -> 19800 | O9: =M9-N9 -> 383204 | P9: =G9*Assumptions!$B$9+H9*Assumptions!$C$9+I9*Assumptions!$D$9+J9*Assumptions!$E$9 -> 119840000 | Q9: =P9*Assumptions!$B$14 -> 83888000 | R9: =P9*Assumptions!$B$15 -> 23968000 | S9: =P9*Assumptions!$B$16 -> 11984000 | T9: =(Q9*Assumptions!$C$14+R9*Assumptions!$C$15)/12 -> 494340
A10: 7 | B10: M7 | C10: 37 | D10: 8 | E10: 5 | F10: 2 | G10: =G9+C10-ROUND(G9*Assumptions!$B$6,0) -> 699 | H10: =H9+D10-ROUND(H9*Assumptions!$C$6,0) -> 40 | I10: =I9+E10-ROUND(I9*Assumptions!$D$6,0) -> 14 | J10: =J9+F10-ROUND(J9*Assumptions!$E$6,0) -> 2 | K10: =SUM(G10:J10) -> 755 | L10: =G10*Assumptions!$B$7+H10*Assumptions!$C$7+I10*Assumptions!$D$7+J10*Assumptions!$E$7 -> 1960800 | M10: =G10*Assumptions!$B$7*Assumptions!$B$8+H10*Assumptions!$C$7*Assumptions!$C$8+I10*Assumptions!$D$7*Assumptions!$D$8+J10*Assumptions!$E$7*Assumptions!$E$8 -> 430472 | N10: =C10*Assumptions!$B$5+D10*Assumptions!$C$5+E10*Assumptions!$D$5+F10*Assumptions!$E$5 -> 22000 | O10: =M10-N10 -> 408472 | P10: =G10*Assumptions!$B$9+H10*Assumptions!$C$9+I10*Assumptions!$D$9+J10*Assumptions!$E$9 -> 128130000 | Q10: =P10*Assumptions!$B$14 -> 89691000 | R10: =P10*Assumptions!$B$15 -> 25626000 | S10: =P10*Assumptions!$B$16 -> 12813000 | T10: =(Q10*Assumptions!$C$14+R10*Assumptions!$C$15)/12 -> 528536.25
A11: 8 | B11: M8 | C11: 34 | D11: 8 | E11: 6 | F11: 2 | G11: =G10+C11-ROUND(G10*Assumptions!$B$6,0) -> 730 | H11: =H10+D11-ROUND(H10*Assumptions!$C$6,0) -> 48 | I11: =I10+E11-ROUND(I10*Assumptions!$D$6,0) -> 20 | J11: =J10+F11-ROUND(J10*Assumptions!$E$6,0) -> 4 | K11: =SUM(G11:J11) -> 802 | L11: =G11*Assumptions!$B$7+H11*Assumptions!$C$7+I11*Assumptions!$D$7+J11*Assumptions!$E$7 -> 2082400 | M11: =G11*Assumptions!$B$7*Assumptions!$B$8+H11*Assumptions!$C$7*Assumptions!$C$8+I11*Assumptions!$D$7*Assumptions!$D$8+J11*Assumptions!$E$7*Assumptions!$E$8 -> 456704 | N11: =C11*Assumptions!$B$5+D11*Assumptions!$C$5+E11*Assumptions!$D$5+F11*Assumptions!$E$5 -> 21200 | O11: =M11-N11 -> 435504 | P11: =G11*Assumptions!$B$9+H11*Assumptions!$C$9+I11*Assumptions!$D$9+J11*Assumptions!$E$9 -> 136060000 | Q11: =P11*Assumptions!$B$14 -> 95242000 | R11: =P11*Assumptions!$B$15 -> 27212000 | S11: =P11*Assumptions!$B$16 -> 13606000 | T11: =(Q11*Assumptions!$C$14+R11*Assumptions!$C$15)/12 -> 561247.5
A12: 9 | B12: M9 | C12: 32 | D12: 8 | E12: 7 | F12: 2 | G12: =G11+C12-ROUND(G11*Assumptions!$B$6,0) -> 758 | H12: =H11+D12-ROUND(H11*Assumptions!$C$6,0) -> 56 | I12: =I11+E12-ROUND(I11*Assumptions!$D$6,0) -> 27 | J12: =J11+F12-ROUND(J11*Assumptions!$E$6,0) -> 6 | K12: =SUM(G12:J12) -> 847 | L12: =G12*Assumptions!$B$7+H12*Assumptions!$C$7+I12*Assumptions!$D$7+J12*Assumptions!$E$7 -> 2198600 | M12: =G12*Assumptions!$B$7*Assumptions!$B$8+H12*Assumptions!$C$7*Assumptions!$C$8+I12*Assumptions!$D$7*Assumptions!$D$8+J12*Assumptions!$E$7*Assumptions!$E$8 -> 481700 | N12: =C12*Assumptions!$B$5+D12*Assumptions!$C$5+E12*Assumptions!$D$5+F12*Assumptions!$E$5 -> 20750 | O12: =M12-N12 -> 460950 | P12: =G12*Assumptions!$B$9+H12*Assumptions!$C$9+I12*Assumptions!$D$9+J12*Assumptions!$E$9 -> 143630000 | Q12: =P12*Assumptions!$B$14 -> 100541000 | R12: =P12*Assumptions!$B$15 -> 28726000 | S12: =P12*Assumptions!$B$16 -> 14363000 | T12: =(Q12*Assumptions!$C$14+R12*Assumptions!$C$15)/12 -> 592473.75
A13: 10 | B13: M10 | C13: 29 | D13: 8 | E13: 8 | F13: 3 | G13: =G12+C13-ROUND(G12*Assumptions!$B$6,0) -> 783 | H13: =H12+D13-ROUND(H12*Assumptions!$C$6,0) -> 64 | I13: =I12+E13-ROUND(I12*Assumptions!$D$6,0) -> 35 | J13: =J12+F13-ROUND(J12*Assumptions!$E$6,0) -> 9 | K13: =SUM(G13:J13) -> 891 | L13: =G13*Assumptions!$B$7+H13*Assumptions!$C$7+I13*Assumptions!$D$7+J13*Assumptions!$E$7 -> 2312300 | M13: =G13*Assumptions!$B$7*Assumptions!$B$8+H13*Assumptions!$C$7*Assumptions!$C$8+I13*Assumptions!$D$7*Assumptions!$D$8+J13*Assumptions!$E$7*Assumptions!$E$8 -> 505982 | N13: =C13*Assumptions!$B$5+D13*Assumptions!$C$5+E13*Assumptions!$D$5+F13*Assumptions!$E$5 -> 21450 | O13: =M13-N13 -> 484532 | P13: =G13*Assumptions!$B$9+H13*Assumptions!$C$9+I13*Assumptions!$D$9+J13*Assumptions!$E$9 -> 151040000 | Q13: =P13*Assumptions!$B$14 -> 105728000 | R13: =P13*Assumptions!$B$15 -> 30208000 | S13: =P13*Assumptions!$B$16 -> 15104000 | T13: =(Q13*Assumptions!$C$14+R13*Assumptions!$C$15)/12 -> 623040
A14: 11 | B14: M11 | C14: 26 | D14: 8 | E14: 9 | F14: 3 | G14: =G13+C14-ROUND(G13*Assumptions!$B$6,0) -> 805 | H14: =H13+D14-ROUND(H13*Assumptions!$C$6,0) -> 71 | I14: =I13+E14-ROUND(I13*Assumptions!$D$6,0) -> 44 | J14: =J13+F14-ROUND(J13*Assumptions!$E$6,0) -> 12 | K14: =SUM(G14:J14) -> 932 | L14: =G14*Assumptions!$B$7+H14*Assumptions!$C$7+I14*Assumptions!$D$7+J14*Assumptions!$E$7 -> 2418000 | M14: =G14*Assumptions!$B$7*Assumptions!$B$8+H14*Assumptions!$C$7*Assumptions!$C$8+I14*Assumptions!$D$7*Assumptions!$D$8+J14*Assumptions!$E$7*Assumptions!$E$8 -> 528456 | N14: =C14*Assumptions!$B$5+D14*Assumptions!$C$5+E14*Assumptions!$D$5+F14*Assumptions!$E$5 -> 20650 | O14: =M14-N14 -> 507806 | P14: =G14*Assumptions!$B$9+H14*Assumptions!$C$9+I14*Assumptions!$D$9+J14*Assumptions!$E$9 -> 157920000 | Q14: =P14*Assumptions!$B$14 -> 110544000 | R14: =P14*Assumptions!$B$15 -> 31584000 | S14: =P14*Assumptions!$B$16 -> 15792000 | T14: =(Q14*Assumptions!$C$14+R14*Assumptions!$C$15)/12 -> 651420
A15: 12 | B15: M12 | C15: 23 | D15: 8 | E15: 10 | F15: 3 | G15: =G14+C15-ROUND(G14*Assumptions!$B$6,0) -> 824 | H15: =H14+D15-ROUND(H14*Assumptions!$C$6,0) -> 78 | I15: =I14+E15-ROUND(I14*Assumptions!$D$6,0) -> 54 | J15: =J14+F15-ROUND(J14*Assumptions!$E$6,0) -> 15 | K15: =SUM(G15:J15) -> 971 | L15: =G15*Assumptions!$B$7+H15*Assumptions!$C$7+I15*Assumptions!$D$7+J15*Assumptions!$E$7 -> 2518300 | M15: =G15*Assumptions!$B$7*Assumptions!$B$8+H15*Assumptions!$C$7*Assumptions!$C$8+I15*Assumptions!$D$7*Assumptions!$D$8+J15*Assumptions!$E$7*Assumptions!$E$8 -> 549694 | N15: =C15*Assumptions!$B$5+D15*Assumptions!$C$5+E15*Assumptions!$D$5+F15*Assumptions!$E$5 -> 19850 | O15: =M15-N15 -> 529844 | P15: =G15*Assumptions!$B$9+H15*Assumptions!$C$9+I15*Assumptions!$D$9+J15*Assumptions!$E$9 -> 164440000 | Q15: =P15*Assumptions!$B$14 -> 115108000 | R15: =P15*Assumptions!$B$15 -> 32888000 | S15: =P15*Assumptions!$B$16 -> 16444000 | T15: =(Q15*Assumptions!$C$14+R15*Assumptions!$C$15)/12 -> 678315
... A39: 36 | B39: M36 | C39: 0 | D39: 0 | E39: 0 | F39: 12 | G39: =G38+C39-ROUND(G38*Assumptions!$B$6,0) -> 811 | H39: =H38+D39-ROUND(H38*Assumptions!$C$6,0) -> 156 | I39: =I38+E39-ROUND(I38*Assumptions!$D$6,0) -> 310 | J39: =J38+F39-ROUND(J38*Assumptions!$E$6,0) -> 156 | K39: =SUM(G39:J39) -> 1433 | L39: =G39*Assumptions!$B$7+H39*Assumptions!$C$7+I39*Assumptions!$D$7+J39*Assumptions!$E$7 -> 3710600 | M39: =G39*Assumptions!$B$7*Assumptions!$B$8+H39*Assumptions!$C$7*Assumptions!$C$8+I39*Assumptions!$D$7*Assumptions!$D$8+J39*Assumptions!$E$7*Assumptions!$E$8 -> 783356 | N39: =C39*Assumptions!$B$5+D39*Assumptions!$C$5+E39*Assumptions!$D$5+F39*Assumptions!$E$5 -> 18000 | O39: =M39-N39 -> 765356 | P39: =G39*Assumptions!$B$9+H39*Assumptions!$C$9+I39*Assumptions!$D$9+J39*Assumptions!$E$9 -> 242090000 | Q39: =P39*Assumptions!$B$14 -> 169463000 | R39: =P39*Assumptions!$B$15 -> 48418000 | S39: =P39*Assumptions!$B$16 -> 24209000 | T39: =(Q39*Assumptions!$C$14+R39*Assumptions!$C$15)/12 -> 998621.25

Sheet Summary
A1: drivEV — Next 1,000 · Model Summary
A3: Opening book (units) | B3: =Assumptions!B18 -> 400
A4: Ending total book — M36 (units) | B4: =Model!K39 -> 1433
A5: Net new units added | B5: =Model!K39-Assumptions!B18 -> 1033
A7: Ending book by channel (units)
A8: B2B Expand | B8: =Model!G39 -> 811
A9: chargEV X-sell | B9: =Model!H39 -> 156
A10: Salary Sacrifice | B10: =Model!I39 -> 310
A11: Direct B2C | B11: =Model!J39 -> 156
A13: Peak asset base (RM) | B13: =MAX(Model!P4:P39) -> 242090000
A14: Peak equity required (RM) | B14: =MAX(Model!S4:S39) -> 24209000
A15: Cumulative CAC spend (RM) | B15: =SUM(Model!N4:N39) -> 689950
A16: Cumulative net contribution after CAC (RM) | B16: =SUM(Model!O4:O39) -> 21405982
A17: Residual value exposure at M36 (RM) | B17: =Model!G39*Assumptions!B9*Assumptions!B10+Model!H39*Assumptions!C9*Assumptions!C10+Model!I39*Assumptions!D9*Assumptions!D10+Model!J39*Assumptions!E9*Assumptions!E10 -> 109399500
A18: RV downside exposure (−15% shock) (RM) | B18: =B17*-Assumptions!B17 -> 16409925
A20: Unit economics by channel
A21: Channel | B21: LTV (RM) | C21: CAC (RM) | D21: LTV:CAC
A22: B2B Expand | B22: =Assumptions!B7*Assumptions!B8*MIN(Assumptions!B11,1/Assumptions!B6) -> 17160 | C22: =Assumptions!B5 -> 350 | D22: =B22/C22 -> 49.03
A23: chargEV X-sell | B23: =Assumptions!C7*Assumptions!C8*MIN(Assumptions!C11,1/Assumptions!C6) -> 17160 | C23: =Assumptions!C5 -> 600 | D23: =B23/C23 -> 28.6
A24: Salary Sacrifice | B24: =Assumptions!D7*Assumptions!D8*MIN(Assumptions!D11,1/Assumptions!D6) -> 11520 | C24: =Assumptions!D5 -> 250 | D24: =B24/C24 -> 46.08
A25: Direct B2C | B25: =Assumptions!E7*Assumptions!E8*MIN(Assumptions!E11,1/Assumptions!E6) -> 9396 | C25: =Assumptions!E5 -> 1500 | D25: =B25/C25 -> 6.26

Sheet Notes
A1: drivEV — Next 1,000 Cohort Model — Notes
A3: Scope: "Next 1,000" = 1,000 net new units on the book (opening ~400 -> ~1,400 over 36 months),
A4: sourced across four channels: B2B land-and-expand, chargEV cross-sell, Salary Sacrifice (the B2B->B2C bridge), Direct B2C.
A6: How to use: edit the Assumptions sheet (rates, capital structure, RV) — the Model and Summary recalculate on open in Excel/Sheets.
A7: Add schedules (Model cols C–F) are editable inputs; book, revenue, contribution, capital are formulas.
A9: Key modelling choices:
A10: • Churn: a subscriber/lessee swap is treated as a TERMINATION (book reduces by churn each month), so churn cannot hide as "continuation".
A11: • Residual value (RV) is the live threat: RV% of cost is an explicit assumption; Summary shows RV exposure at M36 and a -15% downside shock.
A12: Mitigation (not in cashflows): push RV guarantees/buyback onto OEMs/distributors at order time; favour shorter tenor on volatile models.
A13: • Capital is asset-light via an SPV: senior sukuk (cheap, leans on Yinson rating) + mezzanine + thin equity. Edit shares/rates in Assumptions.
A14: • Credit risk: Salary Sacrifice & B2B are payroll/corporate (underwriting largely neutralised); Direct B2C carries the real credit + churn risk (highest CAC, churn, shortest tenor here).
A16: CAVEATS (validate before relying):
... A20: Consumer Credit Act for B2C financing, FSA score-and-refer for insurance). Obtain Malaysian counsel sign-off.
